tree_sitter_builder/__init__.py
tree_sitter_builder/__main__.py
tree_sitter_builder/lib/__init__.py
tree_sitter_builder/lib/dir.py
tree_sitter_builder/lib/main.py
tree_sitter_builder/logging.conf.yml
tree_sitter_builder/subr/__init__.py
tree_sitter_builder/subr/git.py
tree_sitter_builder-0.1.1.dist-info/METADATA
tree_sitter_builder-0.1.1.dist-info/WHEEL
tree_sitter_builder-0.1.1.dist-info/entry_points.txt
tree_sitter_builder-0.1.1.dist-info/RECORD
