Metadata-Version: 2.1
Name: tree-sitter-builder
Version: 0.1.1
Summary: 
License: Apache-2.0
Author: Naoya Yamashita
Author-email: conao3@gmail.com
Requires-Python: >=3.11,<4.0
Classifier: License :: OSI Approved :: Apache Software License
Classifier: Programming Language :: Python :: 3
Classifier: Programming Language :: Python :: 3.11
Requires-Dist: pyyaml (>=6.0.1,<7.0.0)
Requires-Dist: tree-sitter (>=0.20.1,<0.21.0)
